{
  "cards":
  [
    {
      "id": 1,
      "name": "Europaen Underdweller",
      "type": "Soldier",
      "faction": "Europa"
    },
    {
      "id": 2,
      "name": "Ionian Crawler",
      "type": "Mech",
      "faction": "Io"
    },
    {
      "id": 3,
      "name": "Cloud City Fakona",
      "type": "System",
      "faction": "Jupiter"
    },
    {
      "id": 4,
      "name": "Walking City of Callipta",
      "type": "Mech",
      "faction": "Mercury"
    },
    {
      "id": 5,
      "name": "Quartion Proximity Mines",
      "type": "Defenses",
      "faction": "Ceres"
    },
    {
      "id": 6,
      "name": "Venusian Acid Storm",
      "type": "Action",
      "faction": "Venus"
    },
    {
      "id": 7,
      "name": "Titan Cultural Center",
      "type": "System",
      "faction": "Titan"
    }
  ]
}